ankerautotrainsdk/__init__.py
ankerautotrainsdk/model_sdk.py
ankerautotrainsdk/sdk.py
ankerautotrainsdk/types.py
ankerautotrainsdk-0.29.dist-info/METADATA
ankerautotrainsdk-0.29.dist-info/WHEEL
ankerautotrainsdk-0.29.dist-info/top_level.txt
ankerautotrainsdk-0.29.dist-info/RECORD
