Metadata-Version: 2.1
Name: ankerautotrainsdk
Version: 0.29
Summary: Python Package Boilerplate
Home-page: UNKNOWN
Author: taco
Author-email: taco.wang@anker-in.com
License: MIT License
Platform: UNKNOWN
Requires-Python: >=3.6
Requires-Dist: requests (==2.27.1)
Requires-Dist: pydantic (==1.9.2)
Requires-Dist: pycryptodome (==3.21.0)
Requires-Dist: bson (==0.5.10)
Requires-Dist: tqdm (==4.62.3)
Requires-Dist: ujson (==4.3.0)
Requires-Dist: hachoir (==3.3.0)
